gw_settings_management/__init__.py
gw_settings_management/setting_management.py
gw_settings_management/settings_model.py
gw_settings_management-0.5.3.dist-info/METADATA
gw_settings_management-0.5.3.dist-info/WHEEL
gw_settings_management-0.5.3.dist-info/RECORD
