Metadata-Version: 2.3
Name: gw-settings-management
Version: 0.5.3
Summary: Settings management for GW Projects
Author: Chris Moore
Author-email: cmoore@guidewire.com
Requires-Python: >=3.12
Classifier: Programming Language :: Python :: 3
Classifier: Programming Language :: Python :: 3.12
Classifier: Programming Language :: Python :: 3.13
Requires-Dist: python-dotenv (>=1.0.1,<2.0.0)
